LICENSE
MANIFEST.in
README.rst
requirements.txt
setup.py
glopen/__init__.py
glopen/_version.py
glopen/core.py
glopen.egg-info/PKG-INFO
glopen.egg-info/SOURCES.txt
glopen.egg-info/dependency_links.txt
glopen.egg-info/requires.txt
glopen.egg-info/top_level.txt
glopen.egg-info/zip-safe