Metadata-Version: 1.0
Name: glopen
Version: 0.0.9
Summary: Open-like interface to globus remotes
Home-page: http://github.com/maxhutch/glopen/
Author: Max Hutchinson
Author-email: maxhutch@gmail.com
License: MIT
Keywords: globus ssh open
Platform: UNKNOWN
